ftl_playbook/__init__.py
ftl_playbook/cli.py
ftl_playbook/ftl_playbook.py
ftl_playbook/playbook.py
ftl_playbook-0.0.2.dist-info/AUTHORS.rst
ftl_playbook-0.0.2.dist-info/LICENSE
ftl_playbook-0.0.2.dist-info/METADATA
ftl_playbook-0.0.2.dist-info/WHEEL
ftl_playbook-0.0.2.dist-info/entry_points.txt
ftl_playbook-0.0.2.dist-info/top_level.txt
ftl_playbook-0.0.2.dist-info/RECORD
