Metadata-Version: 2.1
Name: ftl-playbook
Version: 0.0.2
Summary: Experiments in speed and scalability
Home-page: https://github.com/benthomasson/ftl_playbook
Author: Ben Thomasson
Author-email: ben.thomasson@gmail.com
License: Apache Software License 2.0
Keywords: ftl_playbook
Platform: UNKNOWN
Classifier: Development Status :: 2 - Pre-Alpha
Classifier: Intended Audience :: Developers
Classifier: License :: OSI Approved :: Apache Software License
Classifier: Natural Language :: English
Classifier: Programming Language :: Python :: 3
Classifier: Programming Language :: Python :: 3.6
Classifier: Programming Language :: Python :: 3.7
Classifier: Programming Language :: Python :: 3.8
Requires-Python: >=3.6
Requires-Dist: faster-than-light
